botw/__init__.py
botw/__version__.py
botw/extensions.py
botw/hashes.py
botw/rstb.py
botw/data/switch_hashes.json
botw/data/wiiu_hashes.json
botw_utils-0.2.3.dist-info/LICENSE
botw_utils-0.2.3.dist-info/METADATA
botw_utils-0.2.3.dist-info/WHEEL
botw_utils-0.2.3.dist-info/top_level.txt
botw_utils-0.2.3.dist-info/RECORD
