Metadata-Version: 2.1
Name: botw-utils
Version: 0.2.3
Summary: Library containing various utilities for modding The Legend of Zelda: Breath of the Wild
Home-page: https://github.com/NiceneNerd/botw-utils
Author: NiceneNerd
Author-email: macadamiadaze@gmail.com
License: UNKNOWN
Platform: UNKNOWN
Classifier: License :: Public Domain
Classifier: Topic :: Software Development :: Libraries
Classifier: Operating System :: OS Independent
Classifier: Programming Language :: Python :: 3 :: Only
Requires-Python: >=3.6
